{
    "repository": "bin",
    "module": "init.lua",
    "path": "modules/bin/share/lua/5.3/bin/init.lua",
    "nodes": [
        {
            "index": 1,
            "master_index": 1,
            "tag": "Var",
            "position": 1,
            "container": "variable",
            "line": 1,
            "lines_count": 1,
            "characters_count": 3,
            "children_count": 1,
            "children": [
                {
                    "index": 1,
                    "master_index": 2,
                    "tag": "Assign",
                    "position": 1,
                    "container": "other",
                    "line": 1,
                    "lines_count": 1,
                    "characters_count": 6,
                    "children_count": 0
                }
            ]
        },
        {
            "index": 2,
            "master_index": 3,
            "tag": "Var",
            "position": 8,
            "container": "variable",
            "line": 2,
            "lines_count": 1,
            "characters_count": 11,
            "children_count": 1,
            "children": [
                {
                    "index": 1,
                    "master_index": 4,
                    "tag": "Assign",
                    "position": 8,
                    "container": "other",
                    "line": 2,
                    "lines_count": 1,
                    "characters_count": 19,
                    "children_count": 0
                }
            ]
        },
        {
            "index": 3,
            "master_index": 5,
            "tag": "Var",
            "position": 28,
            "container": "variable",
            "line": 3,
            "lines_count": 1,
            "characters_count": 9,
            "children_count": 1,
            "children": [
                {
                    "index": 1,
                    "master_index": 6,
                    "tag": "Assign",
                    "position": 28,
                    "container": "other",
                    "line": 3,
                    "lines_count": 1,
                    "characters_count": 18,
                    "children_count": 0
                }
            ]
        },
        {
            "index": 4,
            "master_index": 7,
            "tag": "Var",
            "position": 47,
            "container": "variable",
            "line": 4,
            "lines_count": 1,
            "characters_count": 8,
            "children_count": 1,
            "children": [
                {
                    "index": 1,
                    "master_index": 8,
                    "tag": "Assign",
                    "position": 47,
                    "container": "other",
                    "line": 4,
                    "lines_count": 1,
                    "characters_count": 11,
                    "children_count": 0
                }
            ]
        },
        {
            "index": 5,
            "master_index": 9,
            "tag": "Assign",
            "position": 59,
            "container": "other",
            "line": 5,
            "lines_count": 1,
            "characters_count": 11,
            "children_count": 1,
            "children": [
                {
                    "index": 1,
                    "master_index": 10,
                    "tag": "Var",
                    "position": 59,
                    "container": "variable",
                    "line": 5,
                    "lines_count": 1,
                    "characters_count": 5,
                    "children_count": 0
                }
            ]
        },
        {
            "index": 6,
            "master_index": 11,
            "tag": "Assign",
            "position": 71,
            "container": "other",
            "line": 6,
            "lines_count": 1,
            "characters_count": 17,
            "children_count": 1,
            "children": [
                {
                    "index": 1,
                    "master_index": 12,
                    "tag": "Var",
                    "position": 71,
                    "container": "variable",
                    "line": 6,
                    "lines_count": 1,
                    "characters_count": 11,
                    "children_count": 0
                }
            ]
        },
        {
            "index": 7,
            "master_index": 13,
            "tag": "Var",
            "position": 89,
            "container": "variable",
            "line": 7,
            "lines_count": 1,
            "characters_count": 14,
            "children_count": 1,
            "children": [
                {
                    "index": 1,
                    "master_index": 14,
                    "tag": "Assign",
                    "position": 89,
                    "container": "other",
                    "line": 7,
                    "lines_count": 1,
                    "characters_count": 55,
                    "children_count": 1,
                    "children": [
                        {
                            "index": 1,
                            "master_index": 15,
                            "tag": "Function",
                            "position": 104,
                            "container": "function",
                            "line": 7,
                            "lines_count": 1,
                            "characters_count": 40,
                            "children_count": 0
                        }
                    ]
                }
            ]
        },
        {
            "index": 8,
            "master_index": 16,
            "tag": "Var",
            "position": 145,
            "container": "variable",
            "line": 8,
            "lines_count": 1,
            "characters_count": 9,
            "children_count": 1,
            "children": [
                {
                    "index": 1,
                    "master_index": 17,
                    "tag": "Assign",
                    "position": 145,
                    "container": "other",
                    "line": 8,
                    "lines_count": 1,
                    "characters_count": 52,
                    "children_count": 1,
                    "children": [
                        {
                            "index": 1,
                            "master_index": 18,
                            "tag": "Function",
                            "position": 155,
                            "container": "function",
                            "line": 8,
                            "lines_count": 1,
                            "characters_count": 42,
                            "children_count": 0
                        }
                    ]
                }
            ]
        },
        {
            "index": 9,
            "master_index": 19,
            "tag": "Var",
            "position": 198,
            "container": "variable",
            "line": 9,
            "lines_count": 1,
            "characters_count": 17,
            "children_count": 1,
            "children": [
                {
                    "index": 1,
                    "master_index": 20,
                    "tag": "Assign",
                    "position": 198,
                    "container": "other",
                    "line": 9,
                    "lines_count": 1,
                    "characters_count": 19,
                    "children_count": 0
                }
            ]
        },
        {
            "index": 10,
            "master_index": 21,
            "tag": "Var",
            "position": 218,
            "container": "variable",
            "line": 10,
            "lines_count": 1,
            "characters_count": 11,
            "children_count": 1,
            "children": [
                {
                    "index": 1,
                    "master_index": 22,
                    "tag": "Assign",
                    "position": 218,
                    "container": "other",
                    "line": 10,
                    "lines_count": 1,
                    "characters_count": 14,
                    "children_count": 0
                }
            ]
        },
        {
            "index": 11,
            "master_index": 23,
            "tag": "GlobalFunction",
            "position": 244,
            "container": "function",
            "line": 12,
            "lines_count": 3,
            "characters_count": 94,
            "children_count": 0
        },
        {
            "index": 12,
            "master_index": 24,
            "tag": "GlobalFunction",
            "position": 339,
            "container": "function",
            "line": 15,
            "lines_count": 14,
            "characters_count": 356,
            "children_count": 0
        },
        {
            "index": 13,
            "master_index": 25,
            "tag": "GlobalFunction",
            "position": 696,
            "container": "function",
            "line": 29,
            "lines_count": 7,
            "characters_count": 89,
            "children_count": 0
        },
        {
            "index": 14,
            "master_index": 26,
            "tag": "GlobalFunction",
            "position": 786,
            "container": "function",
            "line": 36,
            "lines_count": 7,
            "characters_count": 114,
            "children_count": 0
        },
        {
            "index": 15,
            "master_index": 27,
            "tag": "GlobalFunction",
            "position": 901,
            "container": "function",
            "line": 43,
            "lines_count": 12,
            "characters_count": 265,
            "children_count": 0
        },
        {
            "index": 16,
            "master_index": 28,
            "tag": "GlobalFunction",
            "position": 1167,
            "container": "function",
            "line": 55,
            "lines_count": 7,
            "characters_count": 114,
            "children_count": 0
        },
        {
            "index": 17,
            "master_index": 29,
            "tag": "GlobalFunction",
            "position": 1282,
            "container": "function",
            "line": 62,
            "lines_count": 8,
            "characters_count": 173,
            "children_count": 0
        },
        {
            "index": 18,
            "master_index": 30,
            "tag": "GlobalFunction",
            "position": 1456,
            "container": "function",
            "line": 70,
            "lines_count": 3,
            "characters_count": 86,
            "children_count": 0
        },
        {
            "index": 19,
            "master_index": 31,
            "tag": "GlobalFunction",
            "position": 1543,
            "container": "function",
            "line": 73,
            "lines_count": 14,
            "characters_count": 332,
            "children_count": 0
        },
        {
            "index": 20,
            "master_index": 32,
            "tag": "GlobalFunction",
            "position": 1876,
            "container": "function",
            "line": 87,
            "lines_count": 4,
            "characters_count": 126,
            "children_count": 0
        },
        {
            "index": 21,
            "master_index": 33,
            "tag": "GlobalFunction",
            "position": 2003,
            "container": "function",
            "line": 91,
            "lines_count": 16,
            "characters_count": 538,
            "children_count": 0
        },
        {
            "index": 22,
            "master_index": 34,
            "tag": "GlobalFunction",
            "position": 2542,
            "container": "function",
            "line": 107,
            "lines_count": 3,
            "characters_count": 61,
            "children_count": 0
        },
        {
            "index": 23,
            "master_index": 35,
            "tag": "GlobalFunction",
            "position": 2604,
            "container": "function",
            "line": 110,
            "lines_count": 3,
            "characters_count": 69,
            "children_count": 0
        },
        {
            "index": 24,
            "master_index": 36,
            "tag": "GlobalFunction",
            "position": 2674,
            "container": "function",
            "line": 113,
            "lines_count": 6,
            "characters_count": 160,
            "children_count": 0
        },
        {
            "index": 25,
            "master_index": 37,
            "tag": "GlobalFunction",
            "position": 2835,
            "container": "function",
            "line": 119,
            "lines_count": 13,
            "characters_count": 493,
            "children_count": 0
        },
        {
            "index": 26,
            "master_index": 38,
            "tag": "GlobalFunction",
            "position": 3329,
            "container": "function",
            "line": 132,
            "lines_count": 10,
            "characters_count": 193,
            "children_count": 0
        },
        {
            "index": 27,
            "master_index": 39,
            "tag": "LocalAssign",
            "position": 3524,
            "container": "other",
            "line": 143,
            "lines_count": 1,
            "characters_count": 9,
            "children_count": 1,
            "children": [
                {
                    "index": 1,
                    "master_index": 40,
                    "tag": "Name",
                    "position": 3530,
                    "container": "variable",
                    "line": 143,
                    "lines_count": 1,
                    "characters_count": 3,
                    "children_count": 0
                }
            ]
        },
        {
            "index": 28,
            "master_index": 41,
            "tag": "If",
            "position": 3534,
            "container": "other",
            "line": 144,
            "lines_count": 7,
            "characters_count": 108,
            "children_count": 3,
            "children": [
                {
                    "index": 1,
                    "master_index": 42,
                    "tag": "Assign",
                    "position": 3547,
                    "container": "other",
                    "line": 145,
                    "lines_count": 1,
                    "characters_count": 18,
                    "children_count": 0
                },
                {
                    "index": 2,
                    "master_index": 43,
                    "tag": "Assign",
                    "position": 3585,
                    "container": "other",
                    "line": 147,
                    "lines_count": 1,
                    "characters_count": 9,
                    "children_count": 0
                },
                {
                    "index": 3,
                    "master_index": 44,
                    "tag": "Assign",
                    "position": 3601,
                    "container": "other",
                    "line": 149,
                    "lines_count": 1,
                    "characters_count": 37,
                    "children_count": 0
                }
            ]
        },
        {
            "index": 29,
            "master_index": 45,
            "tag": "Assign",
            "position": 3643,
            "container": "other",
            "line": 151,
            "lines_count": 1,
            "characters_count": 38,
            "children_count": 0
        },
        {
            "index": 30,
            "master_index": 46,
            "tag": "LocalAssign",
            "position": 3691,
            "container": "other",
            "line": 152,
            "lines_count": 1,
            "characters_count": 13,
            "children_count": 1,
            "children": [
                {
                    "index": 1,
                    "master_index": 47,
                    "tag": "Name",
                    "position": 3697,
                    "container": "variable",
                    "line": 152,
                    "lines_count": 1,
                    "characters_count": 4,
                    "children_count": 0
                }
            ]
        },
        {
            "index": 31,
            "master_index": 48,
            "tag": "Var",
            "position": 3705,
            "container": "variable",
            "line": 153,
            "lines_count": 1,
            "characters_count": 8,
            "children_count": 1,
            "children": [
                {
                    "index": 1,
                    "master_index": 49,
                    "tag": "Assign",
                    "position": 3705,
                    "container": "other",
                    "line": 153,
                    "lines_count": 1,
                    "characters_count": 15,
                    "children_count": 0
                }
            ]
        },
        {
            "index": 32,
            "master_index": 50,
            "tag": "Assign",
            "position": 3721,
            "container": "other",
            "line": 154,
            "lines_count": 1,
            "characters_count": 12,
            "children_count": 1,
            "children": [
                {
                    "index": 1,
                    "master_index": 51,
                    "tag": "Var",
                    "position": 3721,
                    "container": "variable",
                    "line": 154,
                    "lines_count": 1,
                    "characters_count": 9,
                    "children_count": 0
                }
            ]
        },
        {
            "index": 33,
            "master_index": 52,
            "tag": "Assign",
            "position": 3734,
            "container": "other",
            "line": 155,
            "lines_count": 1,
            "characters_count": 13,
            "children_count": 1,
            "children": [
                {
                    "index": 1,
                    "master_index": 53,
                    "tag": "Var",
                    "position": 3734,
                    "container": "variable",
                    "line": 155,
                    "lines_count": 1,
                    "characters_count": 6,
                    "children_count": 0
                }
            ]
        },
        {
            "index": 34,
            "master_index": 54,
            "tag": "Var",
            "position": 3748,
            "container": "variable",
            "line": 156,
            "lines_count": 1,
            "characters_count": 9,
            "children_count": 1,
            "children": [
                {
                    "index": 1,
                    "master_index": 55,
                    "tag": "Assign",
                    "position": 3748,
                    "container": "other",
                    "line": 156,
                    "lines_count": 1,
                    "characters_count": 16,
                    "children_count": 0
                }
            ]
        },
        {
            "index": 35,
            "master_index": 56,
            "tag": "Assign",
            "position": 3765,
            "container": "other",
            "line": 157,
            "lines_count": 1,
            "characters_count": 19,
            "children_count": 1,
            "children": [
                {
                    "index": 1,
                    "master_index": 57,
                    "tag": "Var",
                    "position": 3765,
                    "container": "variable",
                    "line": 157,
                    "lines_count": 1,
                    "characters_count": 12,
                    "children_count": 0
                }
            ]
        },
        {
            "index": 36,
            "master_index": 58,
            "tag": "Var",
            "position": 3785,
            "container": "variable",
            "line": 158,
            "lines_count": 1,
            "characters_count": 15,
            "children_count": 1,
            "children": [
                {
                    "index": 1,
                    "master_index": 59,
                    "tag": "Assign",
                    "position": 3785,
                    "container": "other",
                    "line": 158,
                    "lines_count": 1,
                    "characters_count": 51,
                    "children_count": 1,
                    "children": [
                        {
                            "index": 1,
                            "master_index": 60,
                            "tag": "Function",
                            "position": 3801,
                            "container": "function",
                            "line": 158,
                            "lines_count": 1,
                            "characters_count": 35,
                            "children_count": 0
                        }
                    ]
                }
            ]
        },
        {
            "index": 37,
            "master_index": 61,
            "tag": "Var",
            "position": 3837,
            "container": "variable",
            "line": 159,
            "lines_count": 1,
            "characters_count": 10,
            "children_count": 1,
            "children": [
                {
                    "index": 1,
                    "master_index": 62,
                    "tag": "Assign",
                    "position": 3837,
                    "container": "other",
                    "line": 159,
                    "lines_count": 1,
                    "characters_count": 51,
                    "children_count": 1,
                    "children": [
                        {
                            "index": 1,
                            "master_index": 63,
                            "tag": "Function",
                            "position": 3848,
                            "container": "function",
                            "line": 159,
                            "lines_count": 1,
                            "characters_count": 40,
                            "children_count": 0
                        }
                    ]
                }
            ]
        },
        {
            "index": 38,
            "master_index": 64,
            "tag": "LocalAssign",
            "position": 3889,
            "container": "other",
            "line": 160,
            "lines_count": 1,
            "characters_count": 45,
            "children_count": 2,
            "children": [
                {
                    "index": 1,
                    "master_index": 65,
                    "tag": "Name",
                    "position": 3895,
                    "container": "variable",
                    "line": 160,
                    "lines_count": 1,
                    "characters_count": 5,
                    "children_count": 0
                },
                {
                    "index": 2,
                    "master_index": 66,
                    "tag": "Name",
                    "position": 3901,
                    "container": "variable",
                    "line": 160,
                    "lines_count": 1,
                    "characters_count": 6,
                    "children_count": 0
                }
            ]
        },
        {
            "index": 39,
            "master_index": 67,
            "tag": "GlobalFunction",
            "position": 3935,
            "container": "function",
            "line": 161,
            "lines_count": 3,
            "characters_count": 37,
            "children_count": 0
        },
        {
            "index": 40,
            "master_index": 68,
            "tag": "GlobalFunction",
            "position": 3973,
            "container": "function",
            "line": 164,
            "lines_count": 4,
            "characters_count": 62,
            "children_count": 0
        },
        {
            "index": 41,
            "master_index": 69,
            "tag": "GlobalFunction",
            "position": 4036,
            "container": "function",
            "line": 168,
            "lines_count": 16,
            "characters_count": 376,
            "children_count": 0
        },
        {
            "index": 42,
            "master_index": 70,
            "tag": "Var",
            "position": 4413,
            "container": "variable",
            "line": 184,
            "lines_count": 1,
            "characters_count": 8,
            "children_count": 1,
            "children": [
                {
                    "index": 1,
                    "master_index": 71,
                    "tag": "Assign",
                    "position": 4413,
                    "container": "other",
                    "line": 184,
                    "lines_count": 1,
                    "characters_count": 11,
                    "children_count": 0
                }
            ]
        },
        {
            "index": 43,
            "master_index": 72,
            "tag": "GlobalFunction",
            "position": 4425,
            "container": "function",
            "line": 185,
            "lines_count": 34,
            "characters_count": 687,
            "children_count": 0
        },
        {
            "index": 44,
            "master_index": 73,
            "tag": "GlobalFunction",
            "position": 5113,
            "container": "function",
            "line": 219,
            "lines_count": 20,
            "characters_count": 445,
            "children_count": 0
        },
        {
            "index": 45,
            "master_index": 74,
            "tag": "GlobalFunction",
            "position": 5559,
            "container": "function",
            "line": 239,
            "lines_count": 23,
            "characters_count": 486,
            "children_count": 0
        },
        {
            "index": 46,
            "master_index": 75,
            "tag": "NumericFor",
            "position": 6046,
            "container": "other",
            "line": 262,
            "lines_count": 7,
            "characters_count": 179,
            "children_count": 5,
            "children": [
                {
                    "index": 1,
                    "master_index": 76,
                    "tag": "LocalAssign",
                    "position": 6062,
                    "container": "other",
                    "line": 263,
                    "lines_count": 1,
                    "characters_count": 24,
                    "children_count": 0
                },
                {
                    "index": 2,
                    "master_index": 77,
                    "tag": "Assign",
                    "position": 6088,
                    "container": "other",
                    "line": 264,
                    "lines_count": 1,
                    "characters_count": 57,
                    "children_count": 0
                },
                {
                    "index": 3,
                    "master_index": 78,
                    "tag": "Assign",
                    "position": 6147,
                    "container": "other",
                    "line": 265,
                    "lines_count": 1,
                    "characters_count": 23,
                    "children_count": 0
                },
                {
                    "index": 4,
                    "master_index": 79,
                    "tag": "Assign",
                    "position": 6172,
                    "container": "other",
                    "line": 266,
                    "lines_count": 1,
                    "characters_count": 13,
                    "children_count": 0
                },
                {
                    "index": 5,
                    "master_index": 80,
                    "tag": "Assign",
                    "position": 6187,
                    "container": "other",
                    "line": 267,
                    "lines_count": 1,
                    "characters_count": 34,
                    "children_count": 0
                }
            ]
        },
        {
            "index": 47,
            "master_index": 81,
            "tag": "GlobalFunction",
            "position": 6226,
            "container": "function",
            "line": 269,
            "lines_count": 21,
            "characters_count": 606,
            "children_count": 0
        },
        {
            "index": 48,
            "master_index": 82,
            "tag": "GlobalFunction",
            "position": 6833,
            "container": "function",
            "line": 290,
            "lines_count": 12,
            "characters_count": 231,
            "children_count": 0
        },
        {
            "index": 49,
            "master_index": 83,
            "tag": "GlobalFunction",
            "position": 7065,
            "container": "function",
            "line": 302,
            "lines_count": 7,
            "characters_count": 169,
            "children_count": 0
        },
        {
            "index": 50,
            "master_index": 84,
            "tag": "GlobalFunction",
            "position": 7235,
            "container": "function",
            "line": 309,
            "lines_count": 3,
            "characters_count": 47,
            "children_count": 0
        },
        {
            "index": 51,
            "master_index": 85,
            "tag": "GlobalFunction",
            "position": 7283,
            "container": "function",
            "line": 312,
            "lines_count": 11,
            "characters_count": 197,
            "children_count": 0
        },
        {
            "index": 52,
            "master_index": 86,
            "tag": "GlobalFunction",
            "position": 7481,
            "container": "function",
            "line": 323,
            "lines_count": 7,
            "characters_count": 162,
            "children_count": 0
        },
        {
            "index": 53,
            "master_index": 87,
            "tag": "GlobalFunction",
            "position": 7644,
            "container": "function",
            "line": 330,
            "lines_count": 7,
            "characters_count": 154,
            "children_count": 0
        },
        {
            "index": 54,
            "master_index": 88,
            "tag": "GlobalFunction",
            "position": 7799,
            "container": "function",
            "line": 337,
            "lines_count": 3,
            "characters_count": 44,
            "children_count": 0
        },
        {
            "index": 55,
            "master_index": 89,
            "tag": "GlobalFunction",
            "position": 7844,
            "container": "function",
            "line": 340,
            "lines_count": 3,
            "characters_count": 49,
            "children_count": 0
        },
        {
            "index": 56,
            "master_index": 90,
            "tag": "LocalAssign",
            "position": 7894,
            "container": "require",
            "line": 343,
            "lines_count": 1,
            "characters_count": 42,
            "children_count": 0
        },
        {
            "index": 57,
            "master_index": 91,
            "tag": "LocalAssign",
            "position": 7937,
            "container": "other",
            "line": 344,
            "lines_count": 1,
            "characters_count": 19,
            "children_count": 1,
            "children": [
                {
                    "index": 1,
                    "master_index": 92,
                    "tag": "Name",
                    "position": 7943,
                    "container": "variable",
                    "line": 344,
                    "lines_count": 1,
                    "characters_count": 10,
                    "children_count": 0
                }
            ]
        },
        {
            "index": 58,
            "master_index": 93,
            "tag": "Assign",
            "position": 7957,
            "container": "other",
            "line": 345,
            "lines_count": 1,
            "characters_count": 27,
            "children_count": 1,
            "children": [
                {
                    "index": 1,
                    "master_index": 94,
                    "tag": "Var",
                    "position": 7957,
                    "container": "variable",
                    "line": 345,
                    "lines_count": 1,
                    "characters_count": 14,
                    "children_count": 0
                }
            ]
        },
        {
            "index": 59,
            "master_index": 95,
            "tag": "Assign",
            "position": 7985,
            "container": "other",
            "line": 346,
            "lines_count": 1,
            "characters_count": 18,
            "children_count": 1,
            "children": [
                {
                    "index": 1,
                    "master_index": 96,
                    "tag": "Var",
                    "position": 7985,
                    "container": "variable",
                    "line": 346,
                    "lines_count": 1,
                    "characters_count": 15,
                    "children_count": 0
                }
            ]
        },
        {
            "index": 60,
            "master_index": 97,
            "tag": "Assign",
            "position": 8004,
            "container": "other",
            "line": 347,
            "lines_count": 1,
            "characters_count": 25,
            "children_count": 1,
            "children": [
                {
                    "index": 1,
                    "master_index": 98,
                    "tag": "Var",
                    "position": 8004,
                    "container": "variable",
                    "line": 347,
                    "lines_count": 1,
                    "characters_count": 12,
                    "children_count": 0
                }
            ]
        },
        {
            "index": 61,
            "master_index": 99,
            "tag": "Var",
            "position": 8030,
            "container": "variable",
            "line": 348,
            "lines_count": 1,
            "characters_count": 15,
            "children_count": 1,
            "children": [
                {
                    "index": 1,
                    "master_index": 100,
                    "tag": "Assign",
                    "position": 8030,
                    "container": "other",
                    "line": 348,
                    "lines_count": 1,
                    "characters_count": 28,
                    "children_count": 0
                }
            ]
        },
        {
            "index": 62,
            "master_index": 101,
            "tag": "Var",
            "position": 8059,
            "container": "variable",
            "line": 349,
            "lines_count": 1,
            "characters_count": 18,
            "children_count": 1,
            "children": [
                {
                    "index": 1,
                    "master_index": 102,
                    "tag": "Assign",
                    "position": 8059,
                    "container": "other",
                    "line": 349,
                    "lines_count": 1,
                    "characters_count": 31,
                    "children_count": 0
                }
            ]
        },
        {
            "index": 63,
            "master_index": 103,
            "tag": "Assign",
            "position": 8091,
            "container": "other",
            "line": 350,
            "lines_count": 1,
            "characters_count": 57,
            "children_count": 2,
            "children": [
                {
                    "index": 1,
                    "master_index": 104,
                    "tag": "Var",
                    "position": 8091,
                    "container": "variable",
                    "line": 350,
                    "lines_count": 1,
                    "characters_count": 21,
                    "children_count": 0
                },
                {
                    "index": 2,
                    "master_index": 105,
                    "tag": "Function",
                    "position": 8113,
                    "container": "function",
                    "line": 350,
                    "lines_count": 1,
                    "characters_count": 35,
                    "children_count": 0
                }
            ]
        },
        {
            "index": 64,
            "master_index": 106,
            "tag": "Assign",
            "position": 8149,
            "container": "other",
            "line": 351,
            "lines_count": 1,
            "characters_count": 57,
            "children_count": 2,
            "children": [
                {
                    "index": 1,
                    "master_index": 107,
                    "tag": "Var",
                    "position": 8149,
                    "container": "variable",
                    "line": 351,
                    "lines_count": 1,
                    "characters_count": 16,
                    "children_count": 0
                },
                {
                    "index": 2,
                    "master_index": 108,
                    "tag": "Function",
                    "position": 8166,
                    "container": "function",
                    "line": 351,
                    "lines_count": 1,
                    "characters_count": 40,
                    "children_count": 0
                }
            ]
        },
        {
            "index": 65,
            "master_index": 109,
            "tag": "LocalAssign",
            "position": 8207,
            "container": "other",
            "line": 352,
            "lines_count": 1,
            "characters_count": 45,
            "children_count": 2,
            "children": [
                {
                    "index": 1,
                    "master_index": 110,
                    "tag": "Name",
                    "position": 8213,
                    "container": "variable",
                    "line": 352,
                    "lines_count": 1,
                    "characters_count": 5,
                    "children_count": 0
                },
                {
                    "index": 2,
                    "master_index": 111,
                    "tag": "Name",
                    "position": 8219,
                    "container": "variable",
                    "line": 352,
                    "lines_count": 1,
                    "characters_count": 6,
                    "children_count": 0
                }
            ]
        },
        {
            "index": 66,
            "master_index": 112,
            "tag": "GlobalFunction",
            "position": 8253,
            "container": "function",
            "line": 353,
            "lines_count": 17,
            "characters_count": 440,
            "children_count": 0
        },
        {
            "index": 67,
            "master_index": 113,
            "tag": "GlobalFunction",
            "position": 8694,
            "container": "function",
            "line": 370,
            "lines_count": 8,
            "characters_count": 161,
            "children_count": 0
        },
        {
            "index": 68,
            "master_index": 114,
            "tag": "GlobalFunction",
            "position": 8856,
            "container": "function",
            "line": 378,
            "lines_count": 3,
            "characters_count": 47,
            "children_count": 0
        },
        {
            "index": 69,
            "master_index": 115,
            "tag": "GlobalFunction",
            "position": 8904,
            "container": "function",
            "line": 381,
            "lines_count": 4,
            "characters_count": 72,
            "children_count": 0
        },
        {
            "index": 70,
            "master_index": 116,
            "tag": "Assign",
            "position": 8977,
            "container": "other",
            "line": 385,
            "lines_count": 1,
            "characters_count": 17,
            "children_count": 1,
            "children": [
                {
                    "index": 1,
                    "master_index": 117,
                    "tag": "Var",
                    "position": 8977,
                    "container": "variable",
                    "line": 385,
                    "lines_count": 1,
                    "characters_count": 14,
                    "children_count": 0
                }
            ]
        },
        {
            "index": 71,
            "master_index": 118,
            "tag": "GlobalFunction",
            "position": 8995,
            "container": "function",
            "line": 386,
            "lines_count": 34,
            "characters_count": 711,
            "children_count": 0
        },
        {
            "index": 72,
            "master_index": 119,
            "tag": "GlobalFunction",
            "position": 9707,
            "container": "function",
            "line": 420,
            "lines_count": 20,
            "characters_count": 469,
            "children_count": 0
        },
        {
            "index": 73,
            "master_index": 120,
            "tag": "GlobalFunction",
            "position": 10177,
            "container": "function",
            "line": 440,
            "lines_count": 23,
            "characters_count": 526,
            "children_count": 0
        },
        {
            "index": 74,
            "master_index": 121,
            "tag": "NumericFor",
            "position": 10704,
            "container": "other",
            "line": 463,
            "lines_count": 7,
            "characters_count": 209,
            "children_count": 5,
            "children": [
                {
                    "index": 1,
                    "master_index": 122,
                    "tag": "LocalAssign",
                    "position": 10720,
                    "container": "other",
                    "line": 464,
                    "lines_count": 1,
                    "characters_count": 30,
                    "children_count": 0
                },
                {
                    "index": 2,
                    "master_index": 123,
                    "tag": "Assign",
                    "position": 10752,
                    "container": "other",
                    "line": 465,
                    "lines_count": 1,
                    "characters_count": 63,
                    "children_count": 0
                },
                {
                    "index": 3,
                    "master_index": 124,
                    "tag": "Assign",
                    "position": 10817,
                    "container": "other",
                    "line": 466,
                    "lines_count": 1,
                    "characters_count": 29,
                    "children_count": 0
                },
                {
                    "index": 4,
                    "master_index": 125,
                    "tag": "Assign",
                    "position": 10848,
                    "container": "other",
                    "line": 467,
                    "lines_count": 1,
                    "characters_count": 19,
                    "children_count": 0
                },
                {
                    "index": 5,
                    "master_index": 126,
                    "tag": "Assign",
                    "position": 10869,
                    "container": "other",
                    "line": 468,
                    "lines_count": 1,
                    "characters_count": 40,
                    "children_count": 0
                }
            ]
        },
        {
            "index": 75,
            "master_index": 127,
            "tag": "GlobalFunction",
            "position": 10914,
            "container": "function",
            "line": 470,
            "lines_count": 21,
            "characters_count": 630,
            "children_count": 0
        },
        {
            "index": 76,
            "master_index": 128,
            "tag": "GlobalFunction",
            "position": 11545,
            "container": "function",
            "line": 491,
            "lines_count": 44,
            "characters_count": 1239,
            "children_count": 0
        },
        {
            "index": 77,
            "master_index": 129,
            "tag": "GlobalFunction",
            "position": 12785,
            "container": "function",
            "line": 535,
            "lines_count": 14,
            "characters_count": 295,
            "children_count": 0
        },
        {
            "index": 78,
            "master_index": 130,
            "tag": "GlobalFunction",
            "position": 13081,
            "container": "function",
            "line": 549,
            "lines_count": 7,
            "characters_count": 192,
            "children_count": 0
        },
        {
            "index": 79,
            "master_index": 131,
            "tag": "GlobalFunction",
            "position": 13274,
            "container": "function",
            "line": 556,
            "lines_count": 3,
            "characters_count": 53,
            "children_count": 0
        },
        {
            "index": 80,
            "master_index": 132,
            "tag": "GlobalFunction",
            "position": 13328,
            "container": "function",
            "line": 559,
            "lines_count": 8,
            "characters_count": 131,
            "children_count": 0
        },
        {
            "index": 81,
            "master_index": 133,
            "tag": "GlobalFunction",
            "position": 13460,
            "container": "function",
            "line": 567,
            "lines_count": 7,
            "characters_count": 168,
            "children_count": 0
        },
        {
            "index": 82,
            "master_index": 134,
            "tag": "GlobalFunction",
            "position": 13629,
            "container": "function",
            "line": 574,
            "lines_count": 7,
            "characters_count": 160,
            "children_count": 0
        },
        {
            "index": 83,
            "master_index": 135,
            "tag": "GlobalFunction",
            "position": 13790,
            "container": "function",
            "line": 581,
            "lines_count": 3,
            "characters_count": 50,
            "children_count": 0
        },
        {
            "index": 84,
            "master_index": 136,
            "tag": "GlobalFunction",
            "position": 13841,
            "container": "function",
            "line": 584,
            "lines_count": 3,
            "characters_count": 55,
            "children_count": 0
        },
        {
            "index": 85,
            "master_index": 137,
            "tag": "LocalAssign",
            "position": 13897,
            "container": "require",
            "line": 587,
            "lines_count": 1,
            "characters_count": 45,
            "children_count": 0
        },
        {
            "index": 86,
            "master_index": 138,
            "tag": "GlobalFunction",
            "position": 13943,
            "container": "function",
            "line": 588,
            "lines_count": 3,
            "characters_count": 72,
            "children_count": 0
        },
        {
            "index": 87,
            "master_index": 139,
            "tag": "GlobalFunction",
            "position": 14039,
            "container": "function",
            "line": 592,
            "lines_count": 24,
            "characters_count": 701,
            "children_count": 0
        },
        {
            "index": 88,
            "master_index": 140,
            "tag": "GlobalFunction",
            "position": 14741,
            "container": "function",
            "line": 616,
            "lines_count": 26,
            "characters_count": 797,
            "children_count": 0
        },
        {
            "index": 89,
            "master_index": 141,
            "tag": "GlobalFunction",
            "position": 15539,
            "container": "function",
            "line": 642,
            "lines_count": 16,
            "characters_count": 249,
            "children_count": 0
        },
        {
            "index": 90,
            "master_index": 142,
            "tag": "GlobalFunction",
            "position": 15789,
            "container": "function",
            "line": 658,
            "lines_count": 6,
            "characters_count": 163,
            "children_count": 0
        },
        {
            "index": 91,
            "master_index": 143,
            "tag": "GlobalFunction",
            "position": 15953,
            "container": "function",
            "line": 664,
            "lines_count": 5,
            "characters_count": 125,
            "children_count": 0
        },
        {
            "index": 92,
            "master_index": 144,
            "tag": "GlobalFunction",
            "position": 16096,
            "container": "function",
            "line": 671,
            "lines_count": 11,
            "characters_count": 168,
            "children_count": 0
        },
        {
            "index": 93,
            "master_index": 145,
            "tag": "GlobalFunction",
            "position": 16266,
            "container": "function",
            "line": 683,
            "lines_count": 3,
            "characters_count": 68,
            "children_count": 0
        },
        {
            "index": 94,
            "master_index": 146,
            "tag": "GlobalFunction",
            "position": 16335,
            "container": "function",
            "line": 686,
            "lines_count": 7,
            "characters_count": 192,
            "children_count": 0
        },
        {
            "index": 95,
            "master_index": 147,
            "tag": "GlobalFunction",
            "position": 16528,
            "container": "function",
            "line": 693,
            "lines_count": 28,
            "characters_count": 585,
            "children_count": 0
        },
        {
            "index": 96,
            "master_index": 148,
            "tag": "GlobalFunction",
            "position": 17114,
            "container": "function",
            "line": 721,
            "lines_count": 8,
            "characters_count": 131,
            "children_count": 0
        },
        {
            "index": 97,
            "master_index": 149,
            "tag": "GlobalFunction",
            "position": 17246,
            "container": "function",
            "line": 729,
            "lines_count": 4,
            "characters_count": 89,
            "children_count": 0
        },
        {
            "index": 98,
            "master_index": 150,
            "tag": "GlobalFunction",
            "position": 17336,
            "container": "function",
            "line": 733,
            "lines_count": 10,
            "characters_count": 183,
            "children_count": 0
        },
        {
            "index": 99,
            "master_index": 151,
            "tag": "GlobalFunction",
            "position": 17536,
            "container": "function",
            "line": 744,
            "lines_count": 3,
            "characters_count": 74,
            "children_count": 0
        },
        {
            "index": 100,
            "master_index": 152,
            "tag": "GlobalFunction",
            "position": 17611,
            "container": "function",
            "line": 747,
            "lines_count": 7,
            "characters_count": 116,
            "children_count": 0
        },
        {
            "index": 101,
            "master_index": 153,
            "tag": "GlobalFunction",
            "position": 17728,
            "container": "function",
            "line": 754,
            "lines_count": 7,
            "characters_count": 107,
            "children_count": 0
        },
        {
            "index": 102,
            "master_index": 154,
            "tag": "GlobalFunction",
            "position": 17836,
            "container": "function",
            "line": 761,
            "lines_count": 15,
            "characters_count": 402,
            "children_count": 0
        },
        {
            "index": 103,
            "master_index": 155,
            "tag": "GlobalFunction",
            "position": 18239,
            "container": "function",
            "line": 776,
            "lines_count": 10,
            "characters_count": 206,
            "children_count": 0
        },
        {
            "index": 104,
            "master_index": 156,
            "tag": "GlobalFunction",
            "position": 18446,
            "container": "function",
            "line": 786,
            "lines_count": 24,
            "characters_count": 610,
            "children_count": 0
        },
        {
            "index": 105,
            "master_index": 157,
            "tag": "GlobalFunction",
            "position": 19057,
            "container": "function",
            "line": 810,
            "lines_count": 12,
            "characters_count": 260,
            "children_count": 0
        },
        {
            "index": 106,
            "master_index": 158,
            "tag": "GlobalFunction",
            "position": 19318,
            "container": "function",
            "line": 822,
            "lines_count": 16,
            "characters_count": 282,
            "children_count": 0
        },
        {
            "index": 107,
            "master_index": 159,
            "tag": "GlobalFunction",
            "position": 19601,
            "container": "function",
            "line": 838,
            "lines_count": 25,
            "characters_count": 565,
            "children_count": 0
        },
        {
            "index": 108,
            "master_index": 160,
            "tag": "GlobalFunction",
            "position": 20167,
            "container": "function",
            "line": 863,
            "lines_count": 17,
            "characters_count": 316,
            "children_count": 0
        },
        {
            "index": 109,
            "master_index": 161,
            "tag": "GlobalFunction",
            "position": 20484,
            "container": "function",
            "line": 880,
            "lines_count": 9,
            "characters_count": 190,
            "children_count": 0
        },
        {
            "index": 110,
            "master_index": 162,
            "tag": "GlobalFunction",
            "position": 20675,
            "container": "function",
            "line": 889,
            "lines_count": 15,
            "characters_count": 285,
            "children_count": 0
        },
        {
            "index": 111,
            "master_index": 163,
            "tag": "GlobalFunction",
            "position": 20961,
            "container": "function",
            "line": 904,
            "lines_count": 3,
            "characters_count": 62,
            "children_count": 0
        },
        {
            "index": 112,
            "master_index": 164,
            "tag": "GlobalFunction",
            "position": 21024,
            "container": "function",
            "line": 907,
            "lines_count": 7,
            "characters_count": 193,
            "children_count": 0
        },
        {
            "index": 113,
            "master_index": 165,
            "tag": "GlobalFunction",
            "position": 21218,
            "container": "function",
            "line": 914,
            "lines_count": 12,
            "characters_count": 278,
            "children_count": 0
        },
        {
            "index": 114,
            "master_index": 166,
            "tag": "GlobalFunction",
            "position": 21497,
            "container": "function",
            "line": 926,
            "lines_count": 36,
            "characters_count": 913,
            "children_count": 0
        },
        {
            "index": 115,
            "master_index": 167,
            "tag": "GlobalFunction",
            "position": 22411,
            "container": "function",
            "line": 962,
            "lines_count": 17,
            "characters_count": 585,
            "children_count": 0
        },
        {
            "index": 116,
            "master_index": 168,
            "tag": "Var",
            "position": 22997,
            "container": "variable",
            "line": 979,
            "lines_count": 1,
            "characters_count": 18,
            "children_count": 1,
            "children": [
                {
                    "index": 1,
                    "master_index": 169,
                    "tag": "Assign",
                    "position": 22997,
                    "container": "other",
                    "line": 979,
                    "lines_count": 1,
                    "characters_count": 21,
                    "children_count": 0
                }
            ]
        },
        {
            "index": 117,
            "master_index": 170,
            "tag": "GlobalFunction",
            "position": 23019,
            "container": "function",
            "line": 980,
            "lines_count": 3,
            "characters_count": 82,
            "children_count": 0
        },
        {
            "index": 118,
            "master_index": 171,
            "tag": "GlobalFunction",
            "position": 23102,
            "container": "function",
            "line": 983,
            "lines_count": 78,
            "characters_count": 1720,
            "children_count": 0
        },
        {
            "index": 119,
            "master_index": 172,
            "tag": "GlobalFunction",
            "position": 24823,
            "container": "function",
            "line": 1061,
            "lines_count": 40,
            "characters_count": 987,
            "children_count": 0
        },
        {
            "index": 120,
            "master_index": 173,
            "tag": "GlobalFunction",
            "position": 25811,
            "container": "function",
            "line": 1101,
            "lines_count": 15,
            "characters_count": 296,
            "children_count": 0
        },
        {
            "index": 121,
            "master_index": 174,
            "tag": "GlobalFunction",
            "position": 26108,
            "container": "function",
            "line": 1116,
            "lines_count": 13,
            "characters_count": 266,
            "children_count": 0
        },
        {
            "index": 122,
            "master_index": 175,
            "tag": "GlobalFunction",
            "position": 26375,
            "container": "function",
            "line": 1129,
            "lines_count": 14,
            "characters_count": 338,
            "children_count": 0
        },
        {
            "index": 123,
            "master_index": 176,
            "tag": "GlobalFunction",
            "position": 26714,
            "container": "function",
            "line": 1143,
            "lines_count": 3,
            "characters_count": 43,
            "children_count": 0
        },
        {
            "index": 124,
            "master_index": 177,
            "tag": "GlobalFunction",
            "position": 26758,
            "container": "function",
            "line": 1146,
            "lines_count": 3,
            "characters_count": 43,
            "children_count": 0
        },
        {
            "index": 125,
            "master_index": 178,
            "tag": "GlobalFunction",
            "position": 26827,
            "container": "function",
            "line": 1150,
            "lines_count": 7,
            "characters_count": 153,
            "children_count": 0
        },
        {
            "index": 126,
            "master_index": 179,
            "tag": "GlobalFunction",
            "position": 26981,
            "container": "function",
            "line": 1157,
            "lines_count": 3,
            "characters_count": 63,
            "children_count": 0
        },
        {
            "index": 127,
            "master_index": 180,
            "tag": "GlobalFunction",
            "position": 27045,
            "container": "function",
            "line": 1160,
            "lines_count": 3,
            "characters_count": 61,
            "children_count": 0
        },
        {
            "index": 128,
            "master_index": 181,
            "tag": "GlobalFunction",
            "position": 27107,
            "container": "function",
            "line": 1163,
            "lines_count": 7,
            "characters_count": 178,
            "children_count": 0
        },
        {
            "index": 129,
            "master_index": 182,
            "tag": "GlobalFunction",
            "position": 27286,
            "container": "function",
            "line": 1170,
            "lines_count": 6,
            "characters_count": 165,
            "children_count": 0
        },
        {
            "index": 130,
            "master_index": 183,
            "tag": "GlobalFunction",
            "position": 27452,
            "container": "function",
            "line": 1176,
            "lines_count": 6,
            "characters_count": 158,
            "children_count": 0
        },
        {
            "index": 131,
            "master_index": 184,
            "tag": "GlobalFunction",
            "position": 27611,
            "container": "function",
            "line": 1182,
            "lines_count": 10,
            "characters_count": 182,
            "children_count": 0
        },
        {
            "index": 132,
            "master_index": 185,
            "tag": "GlobalFunction",
            "position": 27794,
            "container": "function",
            "line": 1192,
            "lines_count": 13,
            "characters_count": 218,
            "children_count": 0
        },
        {
            "index": 133,
            "master_index": 186,
            "tag": "LocalAssign",
            "position": 28013,
            "container": "other",
            "line": 1205,
            "lines_count": 1,
            "characters_count": 24,
            "children_count": 1,
            "children": [
                {
                    "index": 1,
                    "master_index": 187,
                    "tag": "Name",
                    "position": 28019,
                    "container": "variable",
                    "line": 1205,
                    "lines_count": 1,
                    "characters_count": 16,
                    "children_count": 0
                }
            ]
        },
        {
            "index": 134,
            "master_index": 188,
            "tag": "Function",
            "position": 28060,
            "container": "function",
            "line": 1206,
            "lines_count": 67,
            "characters_count": 1566,
            "children_count": 0
        },
        {
            "index": 135,
            "master_index": 189,
            "tag": "Function",
            "position": 29627,
            "container": "function",
            "line": 1272,
            "lines_count": 56,
            "characters_count": 2047,
            "children_count": 0
        },
        {
            "index": 136,
            "master_index": 190,
            "tag": "Function",
            "position": 31698,
            "container": "function",
            "line": 1328,
            "lines_count": 3,
            "characters_count": 81,
            "children_count": 0
        },
        {
            "index": 137,
            "master_index": 191,
            "tag": "Function",
            "position": 31780,
            "container": "function",
            "line": 1330,
            "lines_count": 3,
            "characters_count": 57,
            "children_count": 0
        },
        {
            "index": 138,
            "master_index": 192,
            "tag": "Function",
            "position": 31861,
            "container": "function",
            "line": 1333,
            "lines_count": 4,
            "characters_count": 92,
            "children_count": 0
        },
        {
            "index": 139,
            "master_index": 193,
            "tag": "Function",
            "position": 31954,
            "container": "function",
            "line": 1336,
            "lines_count": 4,
            "characters_count": 91,
            "children_count": 0
        },
        {
            "index": 140,
            "master_index": 194,
            "tag": "Function",
            "position": 32069,
            "container": "function",
            "line": 1340,
            "lines_count": 5,
            "characters_count": 123,
            "children_count": 0
        },
        {
            "index": 141,
            "master_index": 195,
            "tag": "Function",
            "position": 32193,
            "container": "function",
            "line": 1344,
            "lines_count": 7,
            "characters_count": 146,
            "children_count": 0
        },
        {
            "index": 142,
            "master_index": 196,
            "tag": "If",
            "position": 32341,
            "container": "other",
            "line": 1351,
            "lines_count": 80,
            "characters_count": 1898,
            "children_count": 11,
            "children": [
                {
                    "index": 1,
                    "master_index": 197,
                    "tag": "GlobalFunction",
                    "position": 32355,
                    "container": "function",
                    "line": 1352,
                    "lines_count": 6,
                    "characters_count": 142,
                    "children_count": 0
                },
                {
                    "index": 2,
                    "master_index": 198,
                    "tag": "GlobalFunction",
                    "position": 32499,
                    "container": "function",
                    "line": 1358,
                    "lines_count": 3,
                    "characters_count": 73,
                    "children_count": 0
                },
                {
                    "index": 3,
                    "master_index": 199,
                    "tag": "GlobalFunction",
                    "position": 32574,
                    "container": "function",
                    "line": 1361,
                    "lines_count": 4,
                    "characters_count": 132,
                    "children_count": 0
                },
                {
                    "index": 4,
                    "master_index": 200,
                    "tag": "GlobalFunction",
                    "position": 32708,
                    "container": "function",
                    "line": 1365,
                    "lines_count": 8,
                    "characters_count": 266,
                    "children_count": 0
                },
                {
                    "index": 5,
                    "master_index": 201,
                    "tag": "GlobalFunction",
                    "position": 32976,
                    "container": "function",
                    "line": 1373,
                    "lines_count": 9,
                    "characters_count": 312,
                    "children_count": 0
                },
                {
                    "index": 6,
                    "master_index": 202,
                    "tag": "GlobalFunction",
                    "position": 33290,
                    "container": "function",
                    "line": 1382,
                    "lines_count": 3,
                    "characters_count": 94,
                    "children_count": 0
                },
                {
                    "index": 7,
                    "master_index": 203,
                    "tag": "GlobalFunction",
                    "position": 33386,
                    "container": "function",
                    "line": 1385,
                    "lines_count": 15,
                    "characters_count": 258,
                    "children_count": 0
                },
                {
                    "index": 8,
                    "master_index": 204,
                    "tag": "GlobalFunction",
                    "position": 33646,
                    "container": "function",
                    "line": 1400,
                    "lines_count": 7,
                    "characters_count": 117,
                    "children_count": 0
                },
                {
                    "index": 9,
                    "master_index": 205,
                    "tag": "GlobalFunction",
                    "position": 33765,
                    "container": "function",
                    "line": 1407,
                    "lines_count": 7,
                    "characters_count": 107,
                    "children_count": 0
                },
                {
                    "index": 10,
                    "master_index": 206,
                    "tag": "GlobalFunction",
                    "position": 33874,
                    "container": "function",
                    "line": 1414,
                    "lines_count": 13,
                    "characters_count": 307,
                    "children_count": 0
                },
                {
                    "index": 11,
                    "master_index": 207,
                    "tag": "GlobalFunction",
                    "position": 34183,
                    "container": "function",
                    "line": 1427,
                    "lines_count": 3,
                    "characters_count": 52,
                    "children_count": 0
                }
            ]
        },
        {
            "index": 143,
            "master_index": 208,
            "tag": "LastStat",
            "position": 34240,
            "container": "other",
            "line": 1431,
            "lines_count": 1,
            "characters_count": 10,
            "children_count": 1,
            "children": [
                {
                    "index": 1,
                    "master_index": 209,
                    "tag": "_SimpleExp",
                    "position": 34247,
                    "container": "interface",
                    "line": 1431,
                    "lines_count": 1,
                    "characters_count": 3,
                    "children_count": 0
                }
            ]
        }
    ],
    "nodes_count": 209,
    "url": "https://raw.githubusercontent.com/katka-juhasova/BP-data/master/modules-part1/bin/share/lua/5.3/bin/init.lua"
}