{
    "repository": "remy",
    "module": "cgilua.lua",
    "path": "BP-data/modules/remy/share/lua/5.3/remy/cgilua.lua",
    "nodes": [
        {
            "index": 1,
            "master_index": 1,
            "tag": "LocalAssign",
            "position": 87,
            "container": "require",
            "line": 5,
            "lines_count": 1,
            "characters_count": 31,
            "children_count": 0
        },
        {
            "index": 2,
            "master_index": 2,
            "tag": "LocalAssign",
            "position": 119,
            "container": "require",
            "line": 6,
            "lines_count": 1,
            "characters_count": 31,
            "children_count": 0
        },
        {
            "index": 3,
            "master_index": 3,
            "tag": "LocalAssign",
            "position": 151,
            "container": "require",
            "line": 7,
            "lines_count": 1,
            "characters_count": 27,
            "children_count": 0
        },
        {
            "index": 4,
            "master_index": 4,
            "tag": "LocalAssign",
            "position": 240,
            "container": "other",
            "line": 10,
            "lines_count": 16,
            "characters_count": 719,
            "children_count": 10,
            "children": [
                {
                    "index": 1,
                    "master_index": 5,
                    "tag": "Name",
                    "position": 246,
                    "container": "variable",
                    "line": 10,
                    "lines_count": 1,
                    "characters_count": 7,
                    "children_count": 0
                },
                {
                    "index": 2,
                    "master_index": 6,
                    "tag": "Function",
                    "position": 307,
                    "container": "function",
                    "line": 12,
                    "lines_count": 1,
                    "characters_count": 45,
                    "children_count": 0
                },
                {
                    "index": 3,
                    "master_index": 7,
                    "tag": "Function",
                    "position": 371,
                    "container": "function",
                    "line": 13,
                    "lines_count": 1,
                    "characters_count": 45,
                    "children_count": 0
                },
                {
                    "index": 4,
                    "master_index": 8,
                    "tag": "Function",
                    "position": 428,
                    "container": "function",
                    "line": 14,
                    "lines_count": 1,
                    "characters_count": 53,
                    "children_count": 0
                },
                {
                    "index": 5,
                    "master_index": 9,
                    "tag": "Function",
                    "position": 495,
                    "container": "function",
                    "line": 15,
                    "lines_count": 1,
                    "characters_count": 55,
                    "children_count": 0
                },
                {
                    "index": 6,
                    "master_index": 10,
                    "tag": "Function",
                    "position": 561,
                    "container": "function",
                    "line": 16,
                    "lines_count": 1,
                    "characters_count": 41,
                    "children_count": 0
                },
                {
                    "index": 7,
                    "master_index": 11,
                    "tag": "Function",
                    "position": 647,
                    "container": "function",
                    "line": 18,
                    "lines_count": 1,
                    "characters_count": 39,
                    "children_count": 0
                },
                {
                    "index": 8,
                    "master_index": 12,
                    "tag": "Function",
                    "position": 701,
                    "container": "function",
                    "line": 19,
                    "lines_count": 1,
                    "characters_count": 38,
                    "children_count": 0
                },
                {
                    "index": 9,
                    "master_index": 13,
                    "tag": "Function",
                    "position": 876,
                    "container": "function",
                    "line": 23,
                    "lines_count": 1,
                    "characters_count": 35,
                    "children_count": 0
                },
                {
                    "index": 10,
                    "master_index": 14,
                    "tag": "Function",
                    "position": 922,
                    "container": "function",
                    "line": 24,
                    "lines_count": 1,
                    "characters_count": 35,
                    "children_count": 0
                }
            ]
        },
        {
            "index": 5,
            "master_index": 15,
            "tag": "LocalAssign",
            "position": 961,
            "container": "other",
            "line": 27,
            "lines_count": 4,
            "characters_count": 52,
            "children_count": 1,
            "children": [
                {
                    "index": 1,
                    "master_index": 16,
                    "tag": "Name",
                    "position": 967,
                    "container": "variable",
                    "line": 27,
                    "lines_count": 1,
                    "characters_count": 1,
                    "children_count": 0
                }
            ]
        },
        {
            "index": 6,
            "master_index": 17,
            "tag": "GlobalFunction",
            "position": 1015,
            "container": "function",
            "line": 32,
            "lines_count": 37,
            "characters_count": 1282,
            "children_count": 0
        },
        {
            "index": 7,
            "master_index": 18,
            "tag": "GlobalFunction",
            "position": 2299,
            "container": "function",
            "line": 70,
            "lines_count": 11,
            "characters_count": 281,
            "children_count": 0
        },
        {
            "index": 8,
            "master_index": 19,
            "tag": "GlobalFunction",
            "position": 2582,
            "container": "function",
            "line": 82,
            "lines_count": 8,
            "characters_count": 192,
            "children_count": 0
        },
        {
            "index": 9,
            "master_index": 20,
            "tag": "GlobalFunction",
            "position": 2776,
            "container": "function",
            "line": 91,
            "lines_count": 4,
            "characters_count": 92,
            "children_count": 0
        },
        {
            "index": 10,
            "master_index": 21,
            "tag": "GlobalFunction",
            "position": 2909,
            "container": "function",
            "line": 97,
            "lines_count": 41,
            "characters_count": 1077,
            "children_count": 0
        },
        {
            "index": 11,
            "master_index": 22,
            "tag": "LastStat",
            "position": 3988,
            "container": "other",
            "line": 139,
            "lines_count": 1,
            "characters_count": 8,
            "children_count": 1,
            "children": [
                {
                    "index": 1,
                    "master_index": 23,
                    "tag": "_SimpleExp",
                    "position": 3995,
                    "container": "interface",
                    "line": 139,
                    "lines_count": 1,
                    "characters_count": 1,
                    "children_count": 0
                }
            ]
        }
    ],
    "nodes_count": 23,
    "url": "https://raw.githubusercontent.com/katka-juhasova/BP-data/master/modules/remy/share/lua/5.3/remy/cgilua.lua"
}