{
    "repository": "aurora",
    "module": "compress.lua",
    "path": "modules/aurora/share/lua/5.3/aurora/httpserver/pegasus/compress.lua",
    "nodes": [
        {
            "index": 1,
            "master_index": 1,
            "tag": "LocalAssign",
            "position": 1,
            "container": "require",
            "line": 1,
            "lines_count": 1,
            "characters_count": 27,
            "children_count": 0
        },
        {
            "index": 2,
            "master_index": 2,
            "tag": "LocalFunction",
            "position": 30,
            "container": "function",
            "line": 3,
            "lines_count": 9,
            "characters_count": 241,
            "children_count": 0
        },
        {
            "index": 3,
            "master_index": 3,
            "tag": "LocalAssign",
            "position": 273,
            "container": "other",
            "line": 13,
            "lines_count": 1,
            "characters_count": 74,
            "children_count": 1,
            "children": [
                {
                    "index": 1,
                    "master_index": 4,
                    "tag": "Name",
                    "position": 279,
                    "container": "variable",
                    "line": 13,
                    "lines_count": 1,
                    "characters_count": 10,
                    "children_count": 0
                }
            ]
        },
        {
            "index": 4,
            "master_index": 5,
            "tag": "LocalAssign",
            "position": 349,
            "container": "other",
            "line": 15,
            "lines_count": 1,
            "characters_count": 21,
            "children_count": 1,
            "children": [
                {
                    "index": 1,
                    "master_index": 6,
                    "tag": "Name",
                    "position": 355,
                    "container": "variable",
                    "line": 15,
                    "lines_count": 1,
                    "characters_count": 10,
                    "children_count": 0
                }
            ]
        },
        {
            "index": 5,
            "master_index": 7,
            "tag": "Do",
            "position": 371,
            "container": "other",
            "line": 15,
            "lines_count": 60,
            "characters_count": 1411,
            "children_count": 8,
            "children": [
                {
                    "index": 1,
                    "master_index": 8,
                    "tag": "Assign",
                    "position": 374,
                    "container": "other",
                    "line": 16,
                    "lines_count": 1,
                    "characters_count": 31,
                    "children_count": 0
                },
                {
                    "index": 2,
                    "master_index": 9,
                    "tag": "Assign",
                    "position": 407,
                    "container": "other",
                    "line": 18,
                    "lines_count": 1,
                    "characters_count": 64,
                    "children_count": 0
                },
                {
                    "index": 3,
                    "master_index": 10,
                    "tag": "Assign",
                    "position": 472,
                    "container": "other",
                    "line": 19,
                    "lines_count": 1,
                    "characters_count": 64,
                    "children_count": 0
                },
                {
                    "index": 4,
                    "master_index": 11,
                    "tag": "Assign",
                    "position": 537,
                    "container": "other",
                    "line": 20,
                    "lines_count": 1,
                    "characters_count": 64,
                    "children_count": 0
                },
                {
                    "index": 5,
                    "master_index": 12,
                    "tag": "Assign",
                    "position": 602,
                    "container": "other",
                    "line": 21,
                    "lines_count": 1,
                    "characters_count": 64,
                    "children_count": 0
                },
                {
                    "index": 6,
                    "master_index": 13,
                    "tag": "Assign",
                    "position": 667,
                    "container": "other",
                    "line": 22,
                    "lines_count": 1,
                    "characters_count": 34,
                    "children_count": 0
                },
                {
                    "index": 7,
                    "master_index": 14,
                    "tag": "Assign",
                    "position": 702,
                    "container": "other",
                    "line": 23,
                    "lines_count": 1,
                    "characters_count": 34,
                    "children_count": 0
                },
                {
                    "index": 8,
                    "master_index": 15,
                    "tag": "If",
                    "position": 738,
                    "container": "other",
                    "line": 25,
                    "lines_count": 48,
                    "characters_count": 1039,
                    "children_count": 6,
                    "children": [
                        {
                            "index": 1,
                            "master_index": 16,
                            "tag": "GlobalFunction",
                            "position": 769,
                            "container": "function",
                            "line": 27,
                            "lines_count": 10,
                            "characters_count": 270,
                            "children_count": 0
                        },
                        {
                            "index": 2,
                            "master_index": 17,
                            "tag": "GlobalFunction",
                            "position": 1041,
                            "container": "function",
                            "line": 38,
                            "lines_count": 3,
                            "characters_count": 67,
                            "children_count": 0
                        },
                        {
                            "index": 3,
                            "master_index": 18,
                            "tag": "GlobalFunction",
                            "position": 1110,
                            "container": "function",
                            "line": 42,
                            "lines_count": 3,
                            "characters_count": 49,
                            "children_count": 0
                        },
                        {
                            "index": 4,
                            "master_index": 19,
                            "tag": "GlobalFunction",
                            "position": 1199,
                            "container": "function",
                            "line": 48,
                            "lines_count": 13,
                            "characters_count": 356,
                            "children_count": 0
                        },
                        {
                            "index": 5,
                            "master_index": 20,
                            "tag": "GlobalFunction",
                            "position": 1557,
                            "container": "function",
                            "line": 62,
                            "lines_count": 4,
                            "characters_count": 90,
                            "children_count": 0
                        },
                        {
                            "index": 6,
                            "master_index": 21,
                            "tag": "GlobalFunction",
                            "position": 1649,
                            "container": "function",
                            "line": 67,
                            "lines_count": 4,
                            "characters_count": 123,
                            "children_count": 0
                        }
                    ]
                }
            ]
        },
        {
            "index": 6,
            "master_index": 22,
            "tag": "LocalAssign",
            "position": 1784,
            "container": "other",
            "line": 76,
            "lines_count": 1,
            "characters_count": 19,
            "children_count": 1,
            "children": [
                {
                    "index": 1,
                    "master_index": 23,
                    "tag": "Name",
                    "position": 1790,
                    "container": "variable",
                    "line": 76,
                    "lines_count": 1,
                    "characters_count": 8,
                    "children_count": 0
                }
            ]
        },
        {
            "index": 7,
            "master_index": 24,
            "tag": "Do",
            "position": 1804,
            "container": "other",
            "line": 76,
            "lines_count": 74,
            "characters_count": 1927,
            "children_count": 7,
            "children": [
                {
                    "index": 1,
                    "master_index": 25,
                    "tag": "Assign",
                    "position": 1807,
                    "container": "other",
                    "line": 77,
                    "lines_count": 1,
                    "characters_count": 27,
                    "children_count": 0
                },
                {
                    "index": 2,
                    "master_index": 26,
                    "tag": "Assign",
                    "position": 1836,
                    "container": "other",
                    "line": 79,
                    "lines_count": 1,
                    "characters_count": 56,
                    "children_count": 0
                },
                {
                    "index": 3,
                    "master_index": 27,
                    "tag": "Assign",
                    "position": 1893,
                    "container": "other",
                    "line": 80,
                    "lines_count": 1,
                    "characters_count": 52,
                    "children_count": 0
                },
                {
                    "index": 4,
                    "master_index": 28,
                    "tag": "Assign",
                    "position": 1946,
                    "container": "other",
                    "line": 81,
                    "lines_count": 1,
                    "characters_count": 58,
                    "children_count": 0
                },
                {
                    "index": 5,
                    "master_index": 29,
                    "tag": "Assign",
                    "position": 2005,
                    "container": "other",
                    "line": 82,
                    "lines_count": 1,
                    "characters_count": 61,
                    "children_count": 0
                },
                {
                    "index": 6,
                    "master_index": 30,
                    "tag": "GlobalFunction",
                    "position": 2068,
                    "container": "function",
                    "line": 84,
                    "lines_count": 7,
                    "characters_count": 130,
                    "children_count": 0
                },
                {
                    "index": 7,
                    "master_index": 31,
                    "tag": "GlobalFunction",
                    "position": 2200,
                    "container": "function",
                    "line": 92,
                    "lines_count": 56,
                    "characters_count": 1526,
                    "children_count": 0
                }
            ]
        },
        {
            "index": 8,
            "master_index": 32,
            "tag": "LastStat",
            "position": 3733,
            "container": "other",
            "line": 151,
            "lines_count": 1,
            "characters_count": 15,
            "children_count": 1,
            "children": [
                {
                    "index": 1,
                    "master_index": 33,
                    "tag": "_SimpleExp",
                    "position": 3740,
                    "container": "interface",
                    "line": 151,
                    "lines_count": 1,
                    "characters_count": 8,
                    "children_count": 0
                }
            ]
        }
    ],
    "nodes_count": 33,
    "url": "https://raw.githubusercontent.com/katka-juhasova/BP-data/master/modules-part1/aurora/share/lua/5.3/aurora/httpserver/pegasus/compress.lua"
}