{
    "repository": "ln",
    "module": "ln.lua",
    "path": "",
    "nodes": [
        {
            "index": 1,
            "master_index": 1,
            "tag": "LocalAssign",
            "position": 1,
            "container": "require",
            "line": 1,
            "lines_count": 1,
            "characters_count": 29,
            "children_count": 0
        },
        {
            "index": 2,
            "master_index": 2,
            "tag": "LocalFunction",
            "position": 32,
            "container": "function",
            "line": 3,
            "lines_count": 3,
            "characters_count": 62,
            "children_count": 0
        },
        {
            "index": 3,
            "master_index": 3,
            "tag": "LocalFunction",
            "position": 96,
            "container": "function",
            "line": 7,
            "lines_count": 7,
            "characters_count": 125,
            "children_count": 0
        },
        {
            "index": 4,
            "master_index": 4,
            "tag": "LocalAssign",
            "position": 223,
            "container": "other",
            "line": 15,
            "lines_count": 1,
            "characters_count": 26,
            "children_count": 1,
            "children": [
                {
                    "index": 1,
                    "master_index": 5,
                    "tag": "Name",
                    "position": 229,
                    "container": "variable",
                    "line": 15,
                    "lines_count": 1,
                    "characters_count": 15,
                    "children_count": 0
                }
            ]
        },
        {
            "index": 5,
            "master_index": 6,
            "tag": "GlobalFunction",
            "position": 251,
            "container": "function",
            "line": 17,
            "lines_count": 8,
            "characters_count": 192,
            "children_count": 0
        },
        {
            "index": 6,
            "master_index": 7,
            "tag": "GlobalFunction",
            "position": 445,
            "container": "function",
            "line": 26,
            "lines_count": 6,
            "characters_count": 106,
            "children_count": 0
        },
        {
            "index": 7,
            "master_index": 8,
            "tag": "LocalAssign",
            "position": 553,
            "container": "other",
            "line": 33,
            "lines_count": 1,
            "characters_count": 24,
            "children_count": 1,
            "children": [
                {
                    "index": 1,
                    "master_index": 9,
                    "tag": "Name",
                    "position": 559,
                    "container": "variable",
                    "line": 33,
                    "lines_count": 1,
                    "characters_count": 13,
                    "children_count": 0
                }
            ]
        },
        {
            "index": 8,
            "master_index": 10,
            "tag": "GlobalFunction",
            "position": 579,
            "container": "function",
            "line": 35,
            "lines_count": 5,
            "characters_count": 88,
            "children_count": 0
        },
        {
            "index": 9,
            "master_index": 11,
            "tag": "GlobalFunction",
            "position": 669,
            "container": "function",
            "line": 41,
            "lines_count": 6,
            "characters_count": 104,
            "children_count": 0
        },
        {
            "index": 10,
            "master_index": 12,
            "tag": "LocalAssign",
            "position": 775,
            "container": "other",
            "line": 48,
            "lines_count": 1,
            "characters_count": 17,
            "children_count": 1,
            "children": [
                {
                    "index": 1,
                    "master_index": 13,
                    "tag": "Name",
                    "position": 781,
                    "container": "variable",
                    "line": 48,
                    "lines_count": 1,
                    "characters_count": 6,
                    "children_count": 0
                }
            ]
        },
        {
            "index": 11,
            "master_index": 14,
            "tag": "GlobalFunction",
            "position": 794,
            "container": "function",
            "line": 50,
            "lines_count": 3,
            "characters_count": 62,
            "children_count": 0
        },
        {
            "index": 12,
            "master_index": 15,
            "tag": "GlobalFunction",
            "position": 858,
            "container": "function",
            "line": 54,
            "lines_count": 19,
            "characters_count": 383,
            "children_count": 0
        },
        {
            "index": 13,
            "master_index": 16,
            "tag": "GlobalFunction",
            "position": 1243,
            "container": "function",
            "line": 74,
            "lines_count": 17,
            "characters_count": 260,
            "children_count": 0
        },
        {
            "index": 14,
            "master_index": 17,
            "tag": "LocalAssign",
            "position": 1505,
            "container": "other",
            "line": 92,
            "lines_count": 1,
            "characters_count": 35,
            "children_count": 1,
            "children": [
                {
                    "index": 1,
                    "master_index": 18,
                    "tag": "Name",
                    "position": 1511,
                    "container": "variable",
                    "line": 92,
                    "lines_count": 1,
                    "characters_count": 14,
                    "children_count": 0
                }
            ]
        },
        {
            "index": 15,
            "master_index": 19,
            "tag": "LocalFunction",
            "position": 1541,
            "container": "function",
            "line": 93,
            "lines_count": 3,
            "characters_count": 53,
            "children_count": 0
        },
        {
            "index": 16,
            "master_index": 20,
            "tag": "LocalFunction",
            "position": 1596,
            "container": "function",
            "line": 97,
            "lines_count": 3,
            "characters_count": 63,
            "children_count": 0
        },
        {
            "index": 17,
            "master_index": 21,
            "tag": "LastStat",
            "position": 1661,
            "container": "other",
            "line": 101,
            "lines_count": 8,
            "characters_count": 160,
            "children_count": 6,
            "children": [
                {
                    "index": 1,
                    "master_index": 22,
                    "tag": "Field",
                    "position": 1672,
                    "container": "interface",
                    "line": 102,
                    "lines_count": 1,
                    "characters_count": 31,
                    "children_count": 0
                },
                {
                    "index": 2,
                    "master_index": 23,
                    "tag": "Field",
                    "position": 1707,
                    "container": "interface",
                    "line": 103,
                    "lines_count": 1,
                    "characters_count": 15,
                    "children_count": 0
                },
                {
                    "index": 3,
                    "master_index": 24,
                    "tag": "Field",
                    "position": 1726,
                    "container": "interface",
                    "line": 104,
                    "lines_count": 1,
                    "characters_count": 33,
                    "children_count": 0
                },
                {
                    "index": 4,
                    "master_index": 25,
                    "tag": "Field",
                    "position": 1763,
                    "container": "interface",
                    "line": 105,
                    "lines_count": 1,
                    "characters_count": 29,
                    "children_count": 0
                },
                {
                    "index": 5,
                    "master_index": 26,
                    "tag": "Field",
                    "position": 1796,
                    "container": "interface",
                    "line": 106,
                    "lines_count": 1,
                    "characters_count": 9,
                    "children_count": 0
                },
                {
                    "index": 6,
                    "master_index": 27,
                    "tag": "Field",
                    "position": 1809,
                    "container": "interface",
                    "line": 107,
                    "lines_count": 1,
                    "characters_count": 9,
                    "children_count": 0
                }
            ]
        }
    ],
    "nodes_count": 27,
    "url": "https://raw.githubusercontent.com/katka-juhasova/BP-data/master/modules-part1/ln/share/lua/5.3/ln.lua"
}